wotw/__init__.py
wotw/inotify.py
wotw/py.typed
wotw/watch.py
wotw-0.1.0.dist-info/LICENSE
wotw-0.1.0.dist-info/WHEEL
wotw-0.1.0.dist-info/METADATA
wotw-0.1.0.dist-info/RECORD
